CHANGES.txt
README.md
setup.py
djinn_likes/__init__.py
djinn_likes/admin.py
djinn_likes/urls.py
djinn_likes/utils.py
djinn_likes.egg-info/PKG-INFO
djinn_likes.egg-info/SOURCES.txt
djinn_likes.egg-info/dependency_links.txt
djinn_likes.egg-info/entry_points.txt
djinn_likes.egg-info/not-zip-safe
djinn_likes.egg-info/requires.txt
djinn_likes.egg-info/top_level.txt
djinn_likes/forms/__init__.py
djinn_likes/forms/like.py
djinn_likes/models/__init__.py
djinn_likes/models/likeable.py
djinn_likes/models/likes.py
djinn_likes/static/js/djinn_likes.js
djinn_likes/templates/djinn_likes/likes.html
djinn_likes/templates/djinn_likes/includes/like_button.html
djinn_likes/templates/djinn_likes/includes/likers.html
djinn_likes/templates/djinn_likes/includes/likes_block.html
djinn_likes/templatetags/__init__.py
djinn_likes/templatetags/djinn_likes.py
djinn_likes/views/__init__.py
djinn_likes/views/like.py